latex_to_image/__init__.py
latex_to_image/crop_img.py
latex_to_image/main.py
latex_to_image/render_latex.py
latex_to_image-0.0.1.dist-info/LICENSE
latex_to_image-0.0.1.dist-info/METADATA
latex_to_image-0.0.1.dist-info/WHEEL
latex_to_image-0.0.1.dist-info/entry_points.txt
latex_to_image-0.0.1.dist-info/top_level.txt
latex_to_image-0.0.1.dist-info/RECORD
